kaptl/Builder.py
kaptl/Common.py
kaptl/KaptlAdd.py
kaptl/KaptlClient.py
kaptl/KaptlInit.py
kaptl/KaptlParse.py
kaptl/KaptlProject.py
kaptl/KaptlShow.py
kaptl/KaptlStatus.py
kaptl/KaptlUpdate.py
kaptl/KaptlVersions.py
kaptl/Utils.py
kaptl/__init__.py
kaptl/exceptions.py
kaptl/main.py
kaptl-0.5.0.9.dist-info/DESCRIPTION.rst
kaptl-0.5.0.9.dist-info/METADATA
kaptl-0.5.0.9.dist-info/RECORD
kaptl-0.5.0.9.dist-info/WHEEL
kaptl-0.5.0.9.dist-info/entry_points.txt
kaptl-0.5.0.9.dist-info/metadata.json
kaptl-0.5.0.9.dist-info/top_level.txt
