Metadata-Version: 2.0
Name: kaptl
Version: 0.5.0.9
Summary: KAPTL generator CLI
Home-page: http://kaptl.com
Author: 8th Sphere, Inc.
Author-email: kaptl@8sph.com
License: MIT
Platform: UNKNOWN
Classifier: Development Status :: 3 - Alpha
Classifier: Environment :: Console
Classifier: Intended Audience :: Developers
Classifier: Operating System :: MacOS :: MacOS X
Classifier: Operating System :: Microsoft :: Windows
Classifier: Operating System :: POSIX
Classifier: Programming Language :: Python
Classifier: Topic :: Software Development
Classifier: Topic :: Utilities
Requires-Dist: colorama (==0.3.6)
Requires-Dist: docopt (==0.6.1)
Requires-Dist: pathspec (==0.5.0)
Requires-Dist: pyprind (==2.9.2)
Requires-Dist: requests (==2.8.0)
Requires-Dist: simplejson (==3.8.1)
